subsystem/__init__.py
subsystem/plugins.py
subsystem/subsystem.py
subsystem-0.5.4.dist-info/DESCRIPTION.rst
subsystem-0.5.4.dist-info/METADATA
subsystem-0.5.4.dist-info/RECORD
subsystem-0.5.4.dist-info/WHEEL
subsystem-0.5.4.dist-info/entry_points.txt
subsystem-0.5.4.dist-info/metadata.json
subsystem-0.5.4.dist-info/top_level.txt
