Metadata-Version: 2.0
Name: subsystem
Version: 0.5.4
Summary: Download and process subtitle files in batch.
Home-page: https://github.com/brbsix/subsystem
Author: Brian Beffa
Author-email: brbsix@gmail.com
License: GPLv3
Keywords: advertising,download,periscope,rename,srt,ss,subscope,subtitle,thunar,yad
Platform: UNKNOWN
Classifier: Development Status :: 4 - Beta
Classifier: Environment :: Console
Classifier: Intended Audience :: Developers
Classifier: Intended Audience :: End Users/Desktop
Classifier: License :: OSI Approved :: GNU General Public License v3 (GPLv3)
Classifier: Natural Language :: English
Classifier: Operating System :: POSIX
Classifier: Operating System :: POSIX :: Linux
Classifier: Programming Language :: Python :: 3
Classifier: Programming Language :: Python :: 3.0
Classifier: Programming Language :: Python :: 3.1
Classifier: Programming Language :: Python :: 3.2
Classifier: Programming Language :: Python :: 3.3
Classifier: Programming Language :: Python :: 3.4
Classifier: Programming Language :: Python :: 3 :: Only
Classifier: Topic :: Multimedia :: Video
Classifier: Topic :: Utilities
Requires-Dist: subnuker
